cccbr_methods/__init__.py
cccbr_methods/models.py
cccbr_methods/update.py
cccbr_methods/data/methods.db
cccbr_methods-1.1.dist-info/LICENSE.txt
cccbr_methods-1.1.dist-info/METADATA
cccbr_methods-1.1.dist-info/WHEEL
cccbr_methods-1.1.dist-info/entry_points.txt
cccbr_methods-1.1.dist-info/top_level.txt
cccbr_methods-1.1.dist-info/RECORD
