Metadata-Version: 2.1
Name: cccbr-methods
Version: 1.1
Summary: A Pythonic interface to the CCCBR Methods Library
Home-page: http://github.com/lelandpaul/cccbr_methods
Author: Leland Paul Kusmer
Author-email: me@lelandpaul.com
License: MIT
Platform: UNKNOWN
Requires-Dist: bs4
Requires-Dist: sqlalchemy
Requires-Dist: lxml
